LICENSE
README.md
setup.py
openquantumcomputing/QAOABase.py
openquantumcomputing/QAOAConstrainedQUBO.py
openquantumcomputing/QAOAExactCover.py
openquantumcomputing/QAOAKhot.py
openquantumcomputing/QAOAMaxCut.py
openquantumcomputing/QAOAMaxKCutBinary.py
openquantumcomputing/QAOAMaxKCutOnehot.py
openquantumcomputing/QAOAPortfolioOptimization.py
openquantumcomputing/QAOAPortfolioOptimization_mixer.py
openquantumcomputing/QAOAQUBO.py
openquantumcomputing/Statistic.py
openquantumcomputing/__init__.py
openquantumcomputing/mixer_utilities.py
openquantumcomputing/utilities.py
openquantumcomputing.egg-info/PKG-INFO
openquantumcomputing.egg-info/SOURCES.txt
openquantumcomputing.egg-info/dependency_links.txt
openquantumcomputing.egg-info/requires.txt
openquantumcomputing.egg-info/top_level.txt