Metadata-Version: 2.1
Name: openquantumcomputing
Version: 1.5
Summary: Tools for quantum computing
Home-page: https://github.com/OpenQuantumComputing/OpenQuantumComputing
Author: Franz Georg Fuchs
Author-email: franzgeorgfuchs@gmail.com
License: GNU General Public License v3.0
Keywords: quantum computing,qaoa,qiskit
License-File: LICENSE
